{"_ts":[1564621321],"_r":{"breakdown":{"html":{"bytes":[128857],"requests":[20]},"js":{"bytes":[10521],"requests":[2]},"css":{"bytes":[3997],"requests":[1]},"image":{"bytes":[3190],"requests":[1]},"flash":{"bytes":[0],"requests":[0]},"font":{"bytes":[464212],"requests":[3]},"video":{"bytes":[0],"requests":[0]},"other":{"bytes":[30657],"requests":[2]}},"date":[1564621321],"domElements":[97],"domInteractive":[921],"firstPaint":[1034.13],"fullyLoaded":[3227],"id":["190801_ZC_2e2e1169553fe5d6f889c2e355bcd6e4"],"loadTime":[1663],"render":[1000],"SpeedIndex":[1015],"TTFB":[897],"videoFrames":[[{"_i":"ms_000000.jpg","_t":0,"_vc":0},{"_i":"ms_001000.jpg","_t":1000,"_vc":98},{"_i":"ms_001600.jpg","_t":1600,"_vc":100},{"_i":"ms_001700.jpg","_t":1700,"_vc":100},{"_i":"ms_001800.jpg","_t":1800,"_vc":100},{"_i":"ms_001900.jpg","_t":1900,"_vc":100},{"_i":"ms_002000.jpg","_t":2000,"_vc":100},{"_i":"ms_002100.jpg","_t":2100,"_vc":99},{"_i":"ms_002300.jpg","_t":2300,"_vc":99},{"_i":"ms_002400.jpg","_t":2400,"_vc":100}]],"visualComplete":[1600],"lighthouse":[100],"pagespeed":[100]}}